mysqllib/__init__.py
mysqllib/database.py
mysqllib/err.py
mysqllib/generator.py
mysqllib/migration.py
mysqllib-1.0.6.dist-info/LICENSE
mysqllib-1.0.6.dist-info/METADATA
mysqllib-1.0.6.dist-info/WHEEL
mysqllib-1.0.6.dist-info/top_level.txt
mysqllib-1.0.6.dist-info/RECORD
