Metadata-Version: 2.1
Name: mysqllib
Version: 1.0.6
Summary: Simple mysql database library
Author: Krzysztof Żyłka
Author-email: krzysztofzylka@yahoo.com
Classifier: Programming Language :: Python :: 3
Classifier: License :: OSI Approved :: MIT License
Classifier: Operating System :: OS Independent
License-File: LICENSE
Requires-Dist: pymysql
